setup.py
kpl_dataset/__init__.py
kpl_dataset/common.py
kpl_dataset/dataset.py
kpl_dataset/define_pb2.py
kpl_dataset/record.py
kpl_dataset_test.egg-info/PKG-INFO
kpl_dataset_test.egg-info/SOURCES.txt
kpl_dataset_test.egg-info/dependency_links.txt
kpl_dataset_test.egg-info/requires.txt
kpl_dataset_test.egg-info/top_level.txt