Metadata-Version: 1.1
Name: kpl-dataset-test
Version: 0.1.2
Summary: KPL Dataset
Home-page: UNKNOWN
Author: UNKNOWN
Author-email: UNKNOWN
License: UNKNOWN
Platform: any
Classifier: Programming Language :: Python
Classifier: Operating System :: OS Independent
